bitcoinmining_sdk/__init__.py
bitcoinmining_sdk/BitcoinMining.pyd
bitcoinmining_sdk/BitcoinMining.so
bitcoinmining_sdk-0.2.2.dist-info/WHEEL
bitcoinmining_sdk-0.2.2.dist-info/METADATA
bitcoinmining_sdk-0.2.2.dist-info/RECORD
