Metadata-Version: 2.1
Name: bitcoinmining-sdk
Version: 0.2.2
Summary: 
Author: DesKaOne
Author-email: DesKaOne@users.noreply.github.com
Requires-Python: >=3.8,<4.0
Classifier: Programming Language :: Python :: 3
Classifier: Programming Language :: Python :: 3.8
Classifier: Programming Language :: Python :: 3.9
Classifier: Programming Language :: Python :: 3.10
Classifier: Programming Language :: Python :: 3.11
Requires-Dist: tuyul-online-sdk (>=0.1.1,<0.2.0)
Requires-Dist: zebedee (>=0.1.3,<0.2.0)
